a2ascanner/__init__.py
a2ascanner/cli.py
a2ascanner/exceptions.py
a2ascanner/api/__init__.py
a2ascanner/api/routes.py
a2ascanner/api/server.py
a2ascanner/config/__init__.py
a2ascanner/config/config.py
a2ascanner/core/__init__.py
a2ascanner/core/models.py
a2ascanner/core/scanner.py
a2ascanner/core/analyzers/__init__.py
a2ascanner/core/analyzers/base.py
a2ascanner/core/analyzers/endpoint_analyzer.py
a2ascanner/core/analyzers/heuristic_analyzer.py
a2ascanner/core/analyzers/llm_analyzer.py
a2ascanner/core/analyzers/spec_analyzer.py
a2ascanner/core/analyzers/yara_analyzer.py
a2ascanner/core/results/__init__.py
a2ascanner/core/results/formatters.py
a2ascanner/core/results/results.py
a2ascanner/core/results/risk_assessor.py
a2ascanner/core/results/statistics.py
a2ascanner/core/threats/__init__.py
a2ascanner/core/threats/threats.py
a2ascanner/data/prompts/protection_rules.md
a2ascanner/data/prompts/threat_analysis_prompt.md
a2ascanner/data/yara_rules/agent_card_spoofing.yara
a2ascanner/data/yara_rules/agent_impersonation.yara
a2ascanner/data/yara_rules/capability_abuse.yara
a2ascanner/data/yara_rules/data_leakage.yara
a2ascanner/data/yara_rules/message_injection.yara
a2ascanner/data/yara_rules/prompt_injection.yara
a2ascanner/data/yara_rules/routing_manipulation.yara
a2ascanner/data/yara_rules/suspicious_agent_endpoint.yara
a2ascanner/data/yara_rules/unauthorized_network_access.yara
a2ascanner/utils/__init__.py
a2ascanner/utils/http_client.py
a2ascanner/utils/logging_config.py
a2ascanner/utils/validators.py
cisco_ai_a2a_scanner-1.0.1.dist-info/licenses/LICENSE
examples/comprehensive_demo.py
examples/example_usage.py
examples/interactive_demo.py
examples/registry_webhook_integration.py
examples/a2a_threat_files/context_poison_writer.py
examples/a2a_threat_files/judge_persuade.py
examples/a2a_threat_files/tool_poison.py
cisco_ai_a2a_scanner-1.0.1.dist-info/METADATA
cisco_ai_a2a_scanner-1.0.1.dist-info/WHEEL
cisco_ai_a2a_scanner-1.0.1.dist-info/entry_points.txt
cisco_ai_a2a_scanner-1.0.1.dist-info/top_level.txt
cisco_ai_a2a_scanner-1.0.1.dist-info/RECORD
