Metadata-Version: 2.4
Name: cisco-ai-a2a-scanner
Version: 1.0.1
Summary: A comprehensive security scanner for Agent-to-Agent (A2A) protocol threats
Author: Cisco
Classifier: Programming Language :: Python :: 3.11
Classifier: Programming Language :: Python :: 3.12
Classifier: Programming Language :: Python :: 3.13
Classifier: Operating System :: OS Independent
Classifier: Intended Audience :: Developers
Classifier: Topic :: Security
Requires-Python: >=3.11
License-File: LICENSE
Requires-Dist: httpx>=0.28.1
Requires-Dist: yara-python>=4.5.4
Requires-Dist: fastapi>=0.110.0
Requires-Dist: uvicorn>=0.29.0
Requires-Dist: pydantic>=2.6.0
Requires-Dist: python-dotenv>=1.0.0
Requires-Dist: litellm>=1.77.0
Requires-Dist: aiohttp>=3.9.0
Requires-Dist: click>=8.1.0
Requires-Dist: rich>=13.7.0
Requires-Dist: jsonschema>=4.20.0
Requires-Dist: requests>=2.31.0
Dynamic: license-file
